sunenergyxt/__init__.py
sunenergyxt/async_client.py
sunenergyxt/client.py
sunenergyxt/constants.py
sunenergyxt/discovery.py
sunenergyxt/exceptions.py
sunenergyxt/models.py
sunenergyxt-1.0.0.dist-info/licenses/LICENSE
sunenergyxt-1.0.0.dist-info/METADATA
sunenergyxt-1.0.0.dist-info/WHEEL
sunenergyxt-1.0.0.dist-info/top_level.txt
sunenergyxt-1.0.0.dist-info/RECORD
