Metadata-Version: 2.4
Name: sunenergyxt
Version: 1.0.0
Summary: Python library for controlling SunEnergyXT (BK215, B215, EV3600) battery storage devices
Author: Sonnenladen GmbH
License: MIT
Project-URL: Homepage, https://github.com/SonnenladenGmbH/sunenergyxt-api
Project-URL: Documentation, https://github.com/SonnenladenGmbH/sunenergyxt-api#readme
Project-URL: Repository, https://github.com/SonnenladenGmbH/sunenergyxt-api
Project-URL: Issues, https://github.com/SonnenladenGmbH/sunenergyxt-api/issues
Keywords: sunenergyxt,bk215,b215,ev3600,battery,storage,home automation,iot,sonnenladen,sunlit
Classifier: Development Status :: 4 - Beta
Classifier: Intended Audience :: Developers
Classifier: Topic :: Home Automation
Classifier: License :: OSI Approved :: MIT License
Classifier: Programming Language :: Python :: 3
Classifier: Programming Language :: Python :: 3.8
Classifier: Programming Language :: Python :: 3.9
Classifier: Programming Language :: Python :: 3.10
Classifier: Programming Language :: Python :: 3.11
Classifier: Programming Language :: Python :: 3.12
Requires-Python: >=3.8
License-File: LICENSE
Requires-Dist: zeroconf>=0.131.0
Provides-Extra: dev
Requires-Dist: pytest>=7.0.0; extra == "dev"
Requires-Dist: pytest-asyncio>=0.21.0; extra == "dev"
Requires-Dist: pytest-cov>=4.0.0; extra == "dev"
Requires-Dist: black>=23.0.0; extra == "dev"
Requires-Dist: flake8>=6.0.0; extra == "dev"
Requires-Dist: mypy>=1.0.0; extra == "dev"
Dynamic: license-file
